<?xml version="1.0" encoding="UTF-8" standalone="yes" ?>


<item>
<title>EVENT  LINK 1</title>
<sportsdevil>http://www.stream2watch.co/streams/113680/1</sportsdevil>
<referer>http://showsport-tv.com/</referer>
</item>



<item>
<title>EVENT LINK 2</title>
<sportsdevil>http://www.stream2watch.co/streams/113619/1</sportsdevil>
<referer>http://showsport-tv.com/</referer>
</item>



<item>
<title>EVENT LINK 3</title>
<sportsdevil>http://www.stream2watch.co/streams/113670/1</sportsdevil>
<referer>http://showsport-tv.com/</referer>
</item>




<item>
<title>USA channels - LINKED SCRAPPED OFF WEBSITES</title>
<sportsdevil>...</sportsdevil>
<referer>http://showsport-tv.com/</referer>
</item>



<item>
<title>A&E</title>
<sportsdevil>http://www.stream2watch.co/streams/29568/1</sportsdevil>
<referer>http://showsport-tv.com/</referer>
</item>



<item>
<title>ABC</title>
<sportsdevil>http://www.stream2watch.co/streams/13285/1</sportsdevil>
<referer>http://showsport-tv.com/</referer>
</item>



<item>
<title>ABC FAMILY</title>
<sportsdevil>http://www.stream2watch.co/streams/35913/1</sportsdevil>
<referer>http://showsport-tv.com/</referer>
</item>



<item>
<title>ABC NEWS</title>
<sportsdevil>http://www.stream2watch.co/streams/75617/1</sportsdevil>
<referer>http://showsport-tv.com/</referer>
</item>



<item>
<title>ALJAZEERA</title>
<sportsdevil>http://www.stream2watch.co/streams/35962/1</sportsdevil>
<referer>http://showsport-tv.com/</referer>
</item>



<item>
<title>AMC</title>
<sportsdevil>http://www.stream2watch.co/streams/35961/1</sportsdevil>
<referer>http://showsport-tv.com/</referer>
</item>



<item>
<title>ANIMAL PLANET</title>
<sportsdevil>http://www.stream2watch.co/streams/26397/1</sportsdevil>
<referer>http://showsport-tv.com/</referer>
</item>



<item>
<title>BET</title>
<sportsdevil>http://www.stream2watch.co/streams/40499/1</sportsdevil>
<referer>http://showsport-tv.com/</referer>
</item>



<item>
<title>BIG TEN</title>
<sportsdevil>http://www.stream2watch.co/streams/61381/1</sportsdevil>
<referer>http://showsport-tv.com/</referer>
</item>



<item>
<title>BLOOMBERG</title>
<sportsdevil>http://www.stream2watch.co/streams/29283/1</sportsdevil>
<referer>http://showsport-tv.com/</referer>
</item>



<item>
<title>BRAVO</title>
<sportsdevil>http://www.stream2watch.co/streams/29266/1</sportsdevil>
<referer>http://showsport-tv.com/</referer>
</item>



<item>
<title></title>
<sportsdevil></sportsdevil>
<referer>http://showsport-tv.com/</referer>
</item>



<item>
<title>C-SPAN</title>
<sportsdevil>http://www.stream2watch.co/streams/34830/1</sportsdevil>
<referer>http://showsport-tv.com/</referer>
</item>



<item>
<title>CARTOON NETWORK</title>
<sportsdevil>http://www.stream2watch.co/streams/34829/1</sportsdevil>
<referer>http://showsport-tv.com/</referer>
</item>



<item>
<title>CBS USA</title>
<sportsdevil>http://www.stream2watch.co/streams/85422/1</sportsdevil>
<referer>http://showsport-tv.com/</referer>
</item>



<item>
<title>CBS NEWS</title>
<sportsdevil>http://www.stream2watch.co/streams/94213/1</sportsdevil>
<referer>http://showsport-tv.com/</referer>
</item>



<item>
<title>CBS SPORTS</title>
<sportsdevil>http://www.stream2watch.co/streams/84457/1</sportsdevil>
<referer>http://showsport-tv.com/</referer>
</item>



<item>
<title>CINEMAX</title>
<sportsdevil>http://www.stream2watch.co/streams/28069/1</sportsdevil>
<referer>http://showsport-tv.com/</referer>
</item>



<item>
<title>CNBC</title>
<sportsdevil>http://www.stream2watch.co/streams/23038/1</sportsdevil>
<referer>http://showsport-tv.com/</referer>
</item>



<item>
<title>CNN</title>
<sportsdevil>http://www.stream2watch.co/streams/21872/1</sportsdevil>
<referer>http://showsport-tv.com/</referer>
</item>



<item>
<title>COMEDY CENTERAL</title>
<sportsdevil>http://www.stream2watch.co/streams/89806/1</sportsdevil>
<referer>http://showsport-tv.com/</referer>
</item>



<item>
<title>CW LIVE</title>
<sportsdevil>http://www.stream2watch.co/streams/22197/1</sportsdevil>
<referer>http://showsport-tv.com/</referer>
</item>



<item>
<title>DISCOVERY</title>
<sportsdevil>http://www.stream2watch.co/streams/18195/1</sportsdevil>
<referer>http://showsport-tv.com/</referer>
</item>



<item>
<title>DISNEY CHANNEL</title>
<sportsdevil>http://www.stream2watch.co/streams/25632/1</sportsdevil>
<referer>http://showsport-tv.com/</referer>
</item>



<item>
<title>ESPN</title>
<sportsdevil>http://www.stream2watch.co/streams/13284/1</sportsdevil>
<referer>http://showsport-tv.com/</referer>
</item>



<item>
<title>ESPN 2</title>
<sportsdevil>http://www.stream2watch.co/streams/25630/1</sportsdevil>
<referer>http://showsport-tv.com/</referer>
</item>



<item>
<title>ESPN 3</title>
<sportsdevil>http://www.stream2watch.co/streams/33880/1</sportsdevil>
<referer>http://showsport-tv.com/</referer>
</item>



<item>
<title>ESPN U</title>
<sportsdevil>http://www.stream2watch.co/streams/34252/1</sportsdevil>
<referer>http://showsport-tv.com/</referer>
</item>



<item>
<title>FOOD NETWORK</title>
<sportsdevil>http://www.stream2watch.co/streams/29351/1</sportsdevil>
<referer>http://showsport-tv.com/</referer>
</item>



<item>
<title>FOX LIVE</title>
<sportsdevil>http://www.stream2watch.co/streams/13472/1</sportsdevil>
<referer>http://showsport-tv.com/</referer>
</item>



<item>
<title>FOX NEWS</title>
<sportsdevil>http://www.stream2watch.co/streams/23114/1</sportsdevil>
<referer>http://showsport-tv.com/</referer>
</item>



<item>
<title>FOX SPORTS</title>
<sportsdevil>http://www.stream2watch.co/streams/24797/1</sportsdevil>
<referer>http://showsport-tv.com/</referer>
</item>



<item>
<title>FOX SPORTS NEWS</title>
<sportsdevil>http://www.stream2watch.co/streams/92945/1</sportsdevil>
<referer>http://showsport-tv.com/</referer>
</item>



<item>
<title>FX LIVE</title>
<sportsdevil>http://www.stream2watch.co/streams/28808/1</sportsdevil>
<referer>http://showsport-tv.com/</referer>
</item>



<item>
<title>GOLF CHANNEL</title>
<sportsdevil>http://www.stream2watch.co/streams/23478/1</sportsdevil>
<referer>http://showsport-tv.com/</referer>
</item>



<item>
<title>HALLMARK</title>
<sportsdevil>http://www.stream2watch.co/streams/56552/1</sportsdevil>
<referer>http://showsport-tv.com/</referer>
</item>



<item>
<title>HBO</title>
<sportsdevil>http://www.stream2watch.co/streams/22192/1</sportsdevil>
<referer>http://showsport-tv.com/</referer>
</item>



<item>
<title>HGTV</title>
<sportsdevil>http://www.stream2watch.co/streams/31002/1</sportsdevil>
<referer>http://showsport-tv.com/</referer>
</item>



<item>
<title>HISTORY CHANNEL</title>
<sportsdevil>http://www.stream2watch.co/streams/29222/1</sportsdevil>
<referer>http://showsport-tv.com/</referer>
</item>



<item>
<title>HLN</title>
<sportsdevil>http://www.stream2watch.co/streams/46853/1</sportsdevil>
<referer>http://showsport-tv.com/</referer>
</item>



<item>
<title>HSN</title>
<sportsdevil>http://www.stream2watch.co/streams/47023/1</sportsdevil>
<referer>http://showsport-tv.com/</referer>
</item>



<item>
<title>I24 NEWS</title>
<sportsdevil>http://www.stream2watch.co/streams/91819/1</sportsdevil>
<referer>http://showsport-tv.com/</referer>
</item>



<item>
<title>ION</title>
<sportsdevil>http://www.stream2watch.co/streams/29352/1</sportsdevil>
<referer>http://showsport-tv.com/</referer>
</item>



<item>
<title>KTLA 5</title>
<sportsdevil>http://www.stream2watch.co/streams/107009/1</sportsdevil>
<referer>http://showsport-tv.com/</referer>
</item>


<item>
<title>LIFETIME</title>
<sportsdevil>http://www.stream2watch.co/streams/36938/1</sportsdevil>
<referer>http://showsport-tv.com/</referer>
</item>

<item>
<title>MLB NETWORK</title>
<sportsdevil>http://www.stream2watch.co/streams/74110/1</sportsdevil>
<referer>http://showsport-tv.com/</referer>
</item>



<item>
<title>MSNBC</title>
<sportsdevil>http://www.stream2watch.co/streams/25662/1</sportsdevil>
<referer>http://showsport-tv.com/</referer>
</item>



<item>
<title>MTV</title>
<sportsdevil>http://www.stream2watch.co/streams/13288/1</sportsdevil>
<referer>http://showsport-tv.com/</referer>
</item>



<item>
<title>NASA TV</title>
<sportsdevil>http://www.stream2watch.co/streams/91818/1</sportsdevil>
<referer>http://showsport-tv.com/</referer>
</item>



<item>
<title>NATIONAL GEO</title>
<sportsdevil></sportsdevil>
<referer>http://showsport-tv.com/</referer>
</item>



<item>
<title>NBA TV</title>
<sportsdevil></sportsdevil>
<referer>http://showsport-tv.com/</referer>
</item>



<item>
<title>NBC</title>
<sportsdevil></sportsdevil>
<referer>http://showsport-tv.com/</referer>
</item>



<item>
<title>NBC SPORTS</title>
<sportsdevil></sportsdevil>
<referer>http://showsport-tv.com/</referer>
</item>



<item>
<title>NFL NETWORK</title>
<sportsdevil></sportsdevil>
<referer>http://showsport-tv.com/</referer>
</item>



<item>
<title>NHL NETWORK</title>
<sportsdevil></sportsdevil>
<referer>http://showsport-tv.com/</referer>
</item>



<item>
<title>NICKELODEON</title>
<sportsdevil></sportsdevil>
<referer>http://showsport-tv.com/</referer>
</item>



<item>
<title>OWN</title>
<sportsdevil>http://www.stream2watch.co/streams/56551/1</sportsdevil>
<referer>http://showsport-tv.com/</referer>
</item>




<item>
<title></title>
<sportsdevil></sportsdevil>
<referer>http://showsport-tv.com/</referer>
</item>





<item>
<title></title>
<sportsdevil></sportsdevil>
<referer>http://showsport-tv.com/</referer>
</item>



<item>
<title></title>
<sportsdevil></sportsdevil>
<referer>http://showsport-tv.com/</referer>
</item>



<item>
<title></title>
<sportsdevil></sportsdevil>
<referer>http://showsport-tv.com/</referer>
</item>



<item>
<title></title>
<sportsdevil></sportsdevil>
<referer>http://showsport-tv.com/</referer>
</item>



<item>
<title></title>
<sportsdevil></sportsdevil>
<referer>http://showsport-tv.com/</referer>
</item>




<item>
<title></title>
<sportsdevil></sportsdevil>
<referer>http://showsport-tv.com/</referer>
</item>



<item>
<title></title>
<sportsdevil></sportsdevil>
<referer>http://showsport-tv.com/</referer>
</item>



<item>
<title></title>
<sportsdevil></sportsdevil>
<referer>http://showsport-tv.com/</referer>
</item>


<item>
<title></title>
<sportsdevil></sportsdevil>
<referer>http://showsport-tv.com/</referer>
</item>





<item>
<title></title>
<sportsdevil></sportsdevil>
<referer>http://showsport-tv.com/</referer>
</item>



<item>
<title></title>
<sportsdevil></sportsdevil>
<referer>http://showsport-tv.com/</referer>
</item>



<item>
<title></title>
<sportsdevil></sportsdevil>
<referer>http://showsport-tv.com/</referer>
</item>



<item>
<title></title>
<sportsdevil></sportsdevil>
<referer>http://showsport-tv.com/</referer>
</item>



<item>
<title></title>
<sportsdevil></sportsdevil>
<referer>http://showsport-tv.com/</referer>
</item>



<item>
<title></title>
<sportsdevil></sportsdevil>
<referer>http://showsport-tv.com/</referer>
</item>



<item>
<title></title>
<sportsdevil></sportsdevil>
<referer>http://showsport-tv.com/</referer>
</item>



<item>
<title></title>
<sportsdevil></sportsdevil>
<referer>http://showsport-tv.com/</referer>
</item>



<item>
<title></title>
<sportsdevil></sportsdevil>
<referer>http://showsport-tv.com/</referer>
</item>



<item>
<title></title>
<sportsdevil></sportsdevil>
<referer>http://showsport-tv.com/</referer>
</item>



<item>
<title></title>
<sportsdevil></sportsdevil>
<referer>http://showsport-tv.com/</referer>
</item>


<item>
<title></title>
<sportsdevil></sportsdevil>
<referer>http://showsport-tv.com/</referer>
</item>


<item>
<title></title>
<sportsdevil></sportsdevil>
<referer>http://showsport-tv.com/</referer>
</item>





<item>
<title></title>
<sportsdevil></sportsdevil>
<referer>http://showsport-tv.com/</referer>
</item>



<item>
<title></title>
<sportsdevil></sportsdevil>
<referer>http://showsport-tv.com/</referer>
</item>



<item>
<title></title>
<sportsdevil></sportsdevil>
<referer>http://showsport-tv.com/</referer>
</item>



<item>
<title></title>
<sportsdevil></sportsdevil>
<referer>http://showsport-tv.com/</referer>
</item>



<item>
<title></title>
<sportsdevil></sportsdevil>
<referer>http://showsport-tv.com/</referer>
</item>



<item>
<title></title>
<sportsdevil></sportsdevil>
<referer>http://showsport-tv.com/</referer>
</item>



<item>
<title></title>
<sportsdevil></sportsdevil>
<referer>http://showsport-tv.com/</referer>
</item>



<item>
<title></title>
<sportsdevil></sportsdevil>
<referer>http://showsport-tv.com/</referer>
</item>



<item>
<title></title>
<sportsdevil></sportsdevil>
<referer>http://showsport-tv.com/</referer>
</item>



<item>
<title></title>
<sportsdevil></sportsdevil>
<referer>http://showsport-tv.com/</referer>
</item>



<item>
<title></title>
<sportsdevil></sportsdevil>
<referer>http://showsport-tv.com/</referer>
</item>


<item>
<title></title>
<sportsdevil></sportsdevil>
<referer>http://showsport-tv.com/</referer>
</item>





<item>
<title></title>
<sportsdevil></sportsdevil>
<referer>http://showsport-tv.com/</referer>
</item>



<item>
<title></title>
<sportsdevil></sportsdevil>
<referer>http://showsport-tv.com/</referer>
</item>



<item>
<title></title>
<sportsdevil></sportsdevil>
<referer>http://showsport-tv.com/</referer>
</item>



<item>
<title></title>
<sportsdevil></sportsdevil>
<referer>http://showsport-tv.com/</referer>
</item>



<item>
<title></title>
<sportsdevil></sportsdevil>
<referer>http://showsport-tv.com/</referer>
</item>



<item>
<title></title>
<sportsdevil></sportsdevil>
<referer>http://showsport-tv.com/</referer>
</item>



<item>
<title></title>
<sportsdevil></sportsdevil>
<referer>http://showsport-tv.com/</referer>
</item>



<item>
<title></title>
<sportsdevil></sportsdevil>
<referer>http://showsport-tv.com/</referer>
</item>



<item>
<title></title>
<sportsdevil></sportsdevil>
<referer>http://showsport-tv.com/</referer>
</item>



<item>
<title></title>
<sportsdevil></sportsdevil>
<referer>http://showsport-tv.com/</referer>
</item>



<item>
<title></title>
<sportsdevil></sportsdevil>
<referer>http://showsport-tv.com/</referer>
</item>


<item>
<title></title>
<sportsdevil></sportsdevil>
<referer>http://showsport-tv.com/</referer>
</item>


<item>
<title></title>
<sportsdevil></sportsdevil>
<referer>http://showsport-tv.com/</referer>
</item>





<item>
<title></title>
<sportsdevil></sportsdevil>
<referer>http://showsport-tv.com/</referer>
</item>



<item>
<title></title>
<sportsdevil></sportsdevil>
<referer>http://showsport-tv.com/</referer>
</item>



<item>
<title></title>
<sportsdevil></sportsdevil>
<referer>http://showsport-tv.com/</referer>
</item>



<item>
<title></title>
<sportsdevil></sportsdevil>
<referer>http://showsport-tv.com/</referer>
</item>



<item>
<title></title>
<sportsdevil></sportsdevil>
<referer>http://showsport-tv.com/</referer>
</item>



<item>
<title></title>
<sportsdevil></sportsdevil>
<referer>http://showsport-tv.com/</referer>
</item>



<item>
<title></title>
<sportsdevil></sportsdevil>
<referer>http://showsport-tv.com/</referer>
</item>



<item>
<title></title>
<sportsdevil></sportsdevil>
<referer>http://showsport-tv.com/</referer>
</item>



<item>
<title></title>
<sportsdevil></sportsdevil>
<referer>http://showsport-tv.com/</referer>
</item>



<item>
<title></title>
<sportsdevil></sportsdevil>
<referer>http://showsport-tv.com/</referer>
</item>



<item>
<title></title>
<sportsdevil></sportsdevil>
<referer>http://showsport-tv.com/</referer>
</item>


<item>
<title></title>
<sportsdevil></sportsdevil>
<referer>http://showsport-tv.com/</referer>
</item>





<item>
<title></title>
<sportsdevil></sportsdevil>
<referer>http://showsport-tv.com/</referer>
</item>



<item>
<title></title>
<sportsdevil></sportsdevil>
<referer>http://showsport-tv.com/</referer>
</item>



<item>
<title></title>
<sportsdevil></sportsdevil>
<referer>http://showsport-tv.com/</referer>
</item>



<item>
<title></title>
<sportsdevil></sportsdevil>
<referer>http://showsport-tv.com/</referer>
</item>



<item>
<title></title>
<sportsdevil></sportsdevil>
<referer>http://showsport-tv.com/</referer>
</item>



<item>
<title></title>
<sportsdevil></sportsdevil>
<referer>http://showsport-tv.com/</referer>
</item>



<item>
<title></title>
<sportsdevil></sportsdevil>
<referer>http://showsport-tv.com/</referer>
</item>



<item>
<title></title>
<sportsdevil></sportsdevil>
<referer>http://showsport-tv.com/</referer>
</item>



<item>
<title></title>
<sportsdevil></sportsdevil>
<referer>http://showsport-tv.com/</referer>
</item>



<item>
<title></title>
<sportsdevil></sportsdevil>
<referer>http://showsport-tv.com/</referer>
</item>



<item>
<title></title>
<sportsdevil></sportsdevil>
<referer>http://showsport-tv.com/</referer>
</item>


<item>
<title></title>
<sportsdevil></sportsdevil>
<referer>http://showsport-tv.com/</referer>
</item>


<item>
<title></title>
<sportsdevil></sportsdevil>
<referer>http://showsport-tv.com/</referer>
</item>





<item>
<title></title>
<sportsdevil></sportsdevil>
<referer>http://showsport-tv.com/</referer>
</item>



<item>
<title></title>
<sportsdevil></sportsdevil>
<referer>http://showsport-tv.com/</referer>
</item>



<item>
<title></title>
<sportsdevil></sportsdevil>
<referer>http://showsport-tv.com/</referer>
</item>



<item>
<title></title>
<sportsdevil></sportsdevil>
<referer>http://showsport-tv.com/</referer>
</item>



<item>
<title></title>
<sportsdevil></sportsdevil>
<referer>http://showsport-tv.com/</referer>
</item>



<item>
<title></title>
<sportsdevil></sportsdevil>
<referer>http://showsport-tv.com/</referer>
</item>



<item>
<title></title>
<sportsdevil></sportsdevil>
<referer>http://showsport-tv.com/</referer>
</item>



<item>
<title></title>
<sportsdevil></sportsdevil>
<referer>http://showsport-tv.com/</referer>
</item>



<item>
<title></title>
<sportsdevil></sportsdevil>
<referer>http://showsport-tv.com/</referer>
</item>



<item>
<title></title>
<sportsdevil></sportsdevil>
<referer>http://showsport-tv.com/</referer>
</item>



<item>
<title></title>
<sportsdevil></sportsdevil>
<referer>http://showsport-tv.com/</referer>
</item>


<item>
<title></title>
<sportsdevil></sportsdevil>
<referer>http://showsport-tv.com/</referer>
</item>





<item>
<title></title>
<sportsdevil></sportsdevil>
<referer>http://showsport-tv.com/</referer>
</item>



<item>
<title></title>
<sportsdevil></sportsdevil>
<referer>http://showsport-tv.com/</referer>
</item>



<item>
<title></title>
<sportsdevil></sportsdevil>
<referer>http://showsport-tv.com/</referer>
</item>



<item>
<title></title>
<sportsdevil></sportsdevil>
<referer>http://showsport-tv.com/</referer>
</item>



<item>
<title></title>
<sportsdevil></sportsdevil>
<referer>http://showsport-tv.com/</referer>
</item>



<item>
<title></title>
<sportsdevil></sportsdevil>
<referer>http://showsport-tv.com/</referer>
</item>



<item>
<title></title>
<sportsdevil></sportsdevil>
<referer>http://showsport-tv.com/</referer>
</item>



<item>
<title></title>
<sportsdevil></sportsdevil>
<referer>http://showsport-tv.com/</referer>
</item>



<item>
<title></title>
<sportsdevil></sportsdevil>
<referer>http://showsport-tv.com/</referer>
</item>



<item>
<title></title>
<sportsdevil></sportsdevil>
<referer>http://showsport-tv.com/</referer>
</item>



<item>
<title></title>
<sportsdevil></sportsdevil>
<referer>http://showsport-tv.com/</referer>
</item>


<item>
<title></title>
<sportsdevil></sportsdevil>
<referer>http://showsport-tv.com/</referer>
</item>


